manim_code_blocks.py
manim_code_blocks_redux-1.0.14.dist-info/LICENSE
manim_code_blocks_redux-1.0.14.dist-info/METADATA
manim_code_blocks_redux-1.0.14.dist-info/WHEEL
manim_code_blocks_redux-1.0.14.dist-info/top_level.txt
manim_code_blocks_redux-1.0.14.dist-info/RECORD
