Metadata-Version: 2.1
Name: manim_code_blocks_redux
Version: 1.0.14
Summary: Animate highlighted blocks of code in Manim
Author: chand1012
License: MIT License
Project-URL: Homepage, https://github.com/CasualCodersProjects/manim-code-blocks
Classifier: License :: OSI Approved :: MIT License
Classifier: Programming Language :: Python :: 3
Classifier: Operating System :: OS Independent
Requires-Python: >=3.9
License-File: LICENSE
Requires-Dist: tokenize-all-code
